mAbLab/__init__.py
mAbLab/common_methods.py
mAbLab/fc_align_and_annotate.py
mAbLab/fc_constants.py
mAbLab/hc_annotator.py
mAbLab/heavy_chain.py
mAbLab/lc_annotator.py
mAbLab/light_chain.py
mAbLab/mab.py
mAbLab/properties.py
mablab-1.1.0.dist-info/licenses/LICENSE
mablab-1.1.0.dist-info/METADATA
mablab-1.1.0.dist-info/WHEEL
mablab-1.1.0.dist-info/top_level.txt
mablab-1.1.0.dist-info/RECORD
