Metadata-Version: 2.4
Name: mAbLab
Version: 1.1.0
Summary: A library for analyzing monoclonal antibody characteristics by domain.
Home-page: https://github.com/PaulNobrega/mAbLab
Author: R. Paul Nobrega
Author-email: paul@paulnobrega.net
Classifier: Programming Language :: Python :: 3
Classifier: License :: OSI Approved :: MIT License
Classifier: Operating System :: OS Independent
Requires-Python: >=3.7
License-File: LICENSE
Requires-Dist: antpack==0.3.6.1
Requires-Dist: biopython
Requires-Dist: numpy
Requires-Dist: Levenshtein
Requires-Dist: ImmuneBuilder
Requires-Dist: pandas
Requires-Dist: scipy
Requires-Dist: torch
Requires-Dist: torchaudio
Requires-Dist: torchvision
Dynamic: author
Dynamic: author-email
Dynamic: classifier
Dynamic: description
Dynamic: description-content-type
Dynamic: home-page
Dynamic: license-file
Dynamic: requires-dist
Dynamic: requires-python
Dynamic: summary
